ndexr_numdata/__init__.py
ndexr_numdata/calculate.py
ndexr_numdata-0.0.1.dist-info/LICENSE
ndexr_numdata-0.0.1.dist-info/METADATA
ndexr_numdata-0.0.1.dist-info/WHEEL
ndexr_numdata-0.0.1.dist-info/top_level.txt
ndexr_numdata-0.0.1.dist-info/RECORD
